{
    "sourceFile": "lib/common_widget/switch_row.dart",
    "activeCommit": 0,
    "commits": [
        {
            "activePatchIndex": 5,
            "patches": [
                {
                    "date": 1722774344205,
                    "content": "Index: \n===================================================================\n--- \n+++ \n"
                },
                {
                    "date": 1724055616669,
                    "content": "Index: \n===================================================================\n--- \n+++ \n@@ -1,7 +1,58 @@\n import 'package:flutter/cupertino.dart';\n import 'package:flutter/material.dart';\n+import 'package:taxi_driver/common/color_extension.dart';\n+\n+class SwitchRow extends StatelessWidget {\n+  final Map sObj;\n+  final Function(bool) didChange;\n+\n+  const SwitchRow({super.key, required this.sObj, required this.didChange});\n+\n+  @override\n+  Widget build(BuildContext context) {\n+    return Container(\n+      padding: const EdgeInsets.symmetric(vertical: 15),\n+      child: Row(\n+        crossAxisAlignment: CrossAxisAlignment.center,\n+        children: [\n+          Expanded(\n+            child: Column(\n+              crossAxisAlignment: CrossAxisAlignment.start,\n+              children: [\n+                Text(\n+                  sObj[\"name\"] as String? ?? \"\",\n+                  style: TextStyle(\n+                    color: TColor.primaryText,\n+                    fontSize: 16,\n+                  ),\n+                ),\n+                const SizedBox(\n+                  height: 4,\n+                ),\n+                Text(\n+                  sObj[\"detail\"] as String? ?? \"\",\n+                  style: TextStyle(\n+                    color: TColor.secondaryText,\n+                    fontSize: 15,\n+                  ),\n+                ),\n+              ],\n+            ),\n+          ),\n+\n+          CupertinoSwitch(value: sObj[\"value\"] as bool? ?? false   , onChanged: didChange)\n+        ],\n+      ),\n+    );\n+  }\n+}\n+\n+\n+\n+/*import 'package:flutter/cupertino.dart';\n import 'package:flutter/material.dart';\n+import 'package:flutter/material.dart';\n import 'package:taxi_driver/common/color_extension.dart';\n \n class SwitchRow extends StatelessWidget {\n   final Map sObj;\n@@ -50,5 +101,5 @@\n                   ],\n                   ),\n                 );\n   }\n-  }\n+  }*/\n"
                },
                {
                    "date": 1724754948718,
                    "content": "Index: \n===================================================================\n--- \n+++ \n@@ -1,6 +1,5 @@\n import 'package:flutter/cupertino.dart';\n-import 'package:flutter/material.dart';\n import 'package:taxi_driver/common/color_extension.dart';\n \n class SwitchRow extends StatelessWidget {\n   final Map sObj;\n"
                },
                {
                    "date": 1725464064242,
                    "content": "Index: \n===================================================================\n--- \n+++ \n@@ -1,5 +1,6 @@\n import 'package:flutter/cupertino.dart';\n+import 'package:flutter/material.dart';\n import 'package:taxi_driver/common/color_extension.dart';\n \n class SwitchRow extends StatelessWidget {\n   final Map sObj;\n"
                },
                {
                    "date": 1725464563782,
                    "content": "Index: \n===================================================================\n--- \n+++ \n@@ -45,61 +45,4 @@\n       ),\n     );\n   }\n }\n-\n-\n-\n-/*import 'package:flutter/cupertino.dart';\n-import 'package:flutter/material.dart';\n-import 'package:flutter/material.dart';\n-import 'package:taxi_driver/common/color_extension.dart';\n-\n-class SwitchRow extends StatelessWidget {\n-  final Map sObj;\n-  final Function(bool) didChange;\n-\n-  const SwitchRow({super.key, required this.sObj, required this.didChange});\n-\n-  @override\n-  Widget build(BuildContext context) {\n-    return Container(\n-                  \n-                  padding: const EdgeInsets.symmetric(vertical: 15, ),\n-                  child: Row(\n-                    crossAxisAlignment: CrossAxisAlignment.center,\n-                    children: [\n-                    Expanded(\n-                      child: Column(\n-                        crossAxisAlignment: CrossAxisAlignment.start,\n-                        children: [\n-                          Text(\n-                                        sObj[\"name\"] as String? ?? \"\",\n-                                        style:  TextStyle(\n-                                          color: TColor.primaryText,\n-                                        fontSize: 16,\n-                                       \n-                                        ),\n-                                      ),\n-                                      const SizedBox(\n-                                        height: 4,),\n-\n-                                      Text(\n-                                        sObj[\"detail\"] as String? ?? \"\",\n-                                        style:  TextStyle(\n-                                          color: TColor.secondaryText,\n-                                        fontSize: 15,\n-                                       \n-                                        ),\n-                                      ),\n-                        ],\n-                      ),\n-                    ),\n-\n-                    CupertinoSwitch(value: sObj[\"value\"] as bool? ?? false , onChanged: didChange)\n-      \n-                   \n-                  ],\n-                  ),\n-                );\n-  }\n-  }*/\n"
                },
                {
                    "date": 1725805229914,
                    "content": "Index: \n===================================================================\n--- \n+++ \n@@ -0,0 +1,48 @@\n+import 'package:flutter/cupertino.dart';\n+import 'package:flutter/material.dart';\n+import 'package:taxi_driver/common/color_extension.dart';\n+\n+class SwitchRow extends StatelessWidget {\n+  final Map sObj;\n+  final Function(bool) didChange;\n+\n+  const SwitchRow({super.key, required this.sObj, required this.didChange});\n+\n+  @override\n+  Widget build(BuildContext context) {\n+    return Container(\n+      padding: const EdgeInsets.symmetric(vertical: 15),\n+      child: Row(\n+        crossAxisAlignment: CrossAxisAlignment.center,\n+        children: [\n+          Expanded(\n+            child: Column(\n+              crossAxisAlignment: CrossAxisAlignment.start,\n+              children: [\n+                Text(\n+                  sObj[\"name\"] as String? ?? \"\",\n+                  style: TextStyle(\n+                    color: TColor.primaryText,\n+                    fontSize: 16,\n+                  ),\n+                ),\n+                const SizedBox(\n+                  height: 4,\n+                ),\n+                Text(\n+                  sObj[\"detail\"] as String? ?? \"\",\n+                  style: TextStyle(\n+                    color: TColor.secondaryText,\n+                    fontSize: 15,\n+                  ),\n+                ),\n+              ],\n+            ),\n+          ),\n+\n+          CupertinoSwitch(value: sObj[\"value\"] as bool? ?? false   , onChanged: didChange)\n+        ],\n+      ),\n+    );\n+  }\n+}\n"
                }
            ],
            "date": 1722774344205,
            "name": "Commit-0",
            "content": "import 'package:flutter/cupertino.dart';\nimport 'package:flutter/material.dart';\nimport 'package:flutter/material.dart';\nimport 'package:taxi_driver/common/color_extension.dart';\n\nclass SwitchRow extends StatelessWidget {\n  final Map sObj;\n  final Function(bool) didChange;\n\n  const SwitchRow({super.key, required this.sObj, required this.didChange});\n\n  @override\n  Widget build(BuildContext context) {\n    return Container(\n                  \n                  padding: const EdgeInsets.symmetric(vertical: 15, ),\n                  child: Row(\n                    crossAxisAlignment: CrossAxisAlignment.center,\n                    children: [\n                    Expanded(\n                      child: Column(\n                        crossAxisAlignment: CrossAxisAlignment.start,\n                        children: [\n                          Text(\n                                        sObj[\"name\"] as String? ?? \"\",\n                                        style:  TextStyle(\n                                          color: TColor.primaryText,\n                                        fontSize: 16,\n                                       \n                                        ),\n                                      ),\n                                      const SizedBox(\n                                        height: 4,),\n\n                                      Text(\n                                        sObj[\"detail\"] as String? ?? \"\",\n                                        style:  TextStyle(\n                                          color: TColor.secondaryText,\n                                        fontSize: 15,\n                                       \n                                        ),\n                                      ),\n                        ],\n                      ),\n                    ),\n\n                    CupertinoSwitch(value: sObj[\"value\"] as bool? ?? false , onChanged: didChange)\n      \n                   \n                  ],\n                  ),\n                );\n  }\n  }\n"
        }
    ]
}